LICENSE
MANIFEST.in
README.rst
setup.py
test.py
area/__init__.py
area.egg-info/PKG-INFO
area.egg-info/SOURCES.txt
area.egg-info/dependency_links.txt
area.egg-info/not-zip-safe
area.egg-info/top_level.txt