Metadata-Version: 1.1
Name: area
Version: 1.1.0
Summary: Calculate the area inside of any GeoJSON geometry. This is a port of Mapbox'sgeojson-area for Python
Home-page: https://github.com/scisco/area
Author: Alireza J (Scisco)
Author-email: scisco7@gmail.com
License: BSD-2-Clause
Keywords: geojson area geometry
Platform: UNKNOWN
Classifier: Intended Audience :: Developers
Classifier: Intended Audience :: Science/Research
Classifier: Topic :: Scientific/Engineering :: GIS
Classifier: License :: OSI Approved :: BSD License
Classifier: Programming Language :: Python :: 2.6
Classifier: Programming Language :: Python :: 2.7
Classifier: Programming Language :: Python :: 3.3
Classifier: Programming Language :: Python :: 3.4
